heroku_bouncer.py
setup.py
heroku_bouncer.egg-info/PKG-INFO
heroku_bouncer.egg-info/SOURCES.txt
heroku_bouncer.egg-info/dependency_links.txt
heroku_bouncer.egg-info/requires.txt
heroku_bouncer.egg-info/top_level.txt