Metadata-Version: 1.1
Name: heroku-bouncer
Version: 1.2
Summary: WSGI middleware that requires Heroku OAuth for all requests.
Home-page: http://github.com/heroku/heroku-bouncer-python
Author: Jacob Kaplan-Moss
Author-email: jacob@heroku.com
License: UNKNOWN
Platform: UNKNOWN
Classifier: Development Status :: 4 - Beta
Classifier: Environment :: Web Environment
Classifier: Intended Audience :: Developers
Classifier: Intended Audience :: System Administrators
Classifier: License :: OSI Approved :: BSD License
Classifier: Programming Language :: Python :: 2.7
Classifier: Topic :: Internet :: WWW/HTTP :: WSGI :: Middleware
